sambuca_core/__init__.py
sambuca_core/constants.py
sambuca_core/exceptions.py
sambuca_core/forward_model.py
sambuca_core/sensor_filter.py
sambuca_core/spectra_operations.py
sambuca_core/spectra_readers.py
sambuca_core/tests/__init__.py
sambuca_core/tests/test_forward_model.py
sambuca_core/tests/test_sensor_filter.py
sambuca_core/tests/test_sensor_filter_loading.py
sambuca_core/tests/test_spectra_loading.py
sambuca_core/tests/test_spectra_operations.py
sambuca_core/tests/test_utility_numpy.py
sambuca_core/utility/__init__.py
sambuca_core/utility/collections.py
sambuca_core/utility/numpy.py
sambuca_core/utility/os.py
sambuca_core-1.3.3.dist-info/METADATA
sambuca_core-1.3.3.dist-info/RECORD
sambuca_core-1.3.3.dist-info/WHEEL
sambuca_core-1.3.3.dist-info/top_level.txt
sambuca_core-1.3.3.dist-info/zip-safe
